odoo/addons/test_queue_job/README.rst
odoo/addons/test_queue_job/__init__.py
odoo/addons/test_queue_job/__manifest__.py
odoo/addons/test_queue_job/i18n/test_queue_job.pot
odoo/addons/test_queue_job/models/__init__.py
odoo/addons/test_queue_job/models/test_models.py
odoo/addons/test_queue_job/security/ir.model.access.csv
odoo/addons/test_queue_job/static/description/icon.png
odoo/addons/test_queue_job/tests/__init__.py
odoo/addons/test_queue_job/tests/test_job.py
odoo/addons/test_queue_job/tests/test_job_channels.py
odoo/addons/test_queue_job/tests/test_related_actions.py
odoo11_addon_test_queue_job-11.0.1.1.0.dist-info/METADATA
odoo11_addon_test_queue_job-11.0.1.1.0.dist-info/WHEEL
odoo11_addon_test_queue_job-11.0.1.1.0.dist-info/top_level.txt
odoo11_addon_test_queue_job-11.0.1.1.0.dist-info/RECORD
